netbox_metatype_importer/__init__.py
netbox_metatype_importer/choices.py
netbox_metatype_importer/filters.py
netbox_metatype_importer/forms.py
netbox_metatype_importer/models.py
netbox_metatype_importer/navigation.py
netbox_metatype_importer/tables.py
netbox_metatype_importer/urls.py
netbox_metatype_importer/utils.py
netbox_metatype_importer/views.py
netbox_metatype_importer/api/__init__.py
netbox_metatype_importer/api/serializers.py
netbox_metatype_importer/api/urls.py
netbox_metatype_importer/api/views.py
netbox_metatype_importer/graphql/__init__.py
netbox_metatype_importer/graphql/gql.py
netbox_metatype_importer/jobs/__init__.py
netbox_metatype_importer/jobs/load_devicetype.py
netbox_metatype_importer/migrations/0001_initial.py
netbox_metatype_importer/migrations/__init__.py
netbox_metatype_importer/templates/netbox_metatype_importer/metadevicetype_list.html
netbox_metatype_importer/templates/netbox_metatype_importer/metamoduletype_list.html
netbox_metatype_importer/tests/__init__.py
netbox_metatype_importer/tests/test_filtersets.py
netbox_metatype_importer/tests/test_graphql_proxies.py
netbox_metatype_importer/tests/test_models.py
netbox_metatype_importer-0.7.1.dist-info/licenses/LICENSE
netbox_metatype_importer-0.7.1.dist-info/METADATA
netbox_metatype_importer-0.7.1.dist-info/WHEEL
netbox_metatype_importer-0.7.1.dist-info/top_level.txt
netbox_metatype_importer-0.7.1.dist-info/RECORD
