Metadata-Version: 2.4
Name: netbox-metatype-importer
Version: 0.7.1
Summary: Easily import Device and Module types from GitHub repo
Home-page: https://github.com/Onemind-Services-LLC/netbox-metatype-importer
Author: Abhimanyu Saharan
Author-email: asaharan@onemindservices.com
Maintainer: Prince Kumar
Maintainer-email: pkumar@onemindservices.com
Classifier: Development Status :: 3 - Alpha
Classifier: Framework :: Django
Classifier: Programming Language :: Python :: 3
License-File: LICENSE
Dynamic: author
Dynamic: author-email
Dynamic: classifier
Dynamic: description
Dynamic: description-content-type
Dynamic: home-page
Dynamic: license-file
Dynamic: maintainer
Dynamic: maintainer-email
Dynamic: summary
